{
  "generated_at": "2026-06-03T06:11:37Z",
  "yesterday_date": "2026-06-02",
  "trial_days": 42,
  "hubs": [
    {
      "hub_name": "Kajola Ondo",
      "hub_id": 274,
      "yesterday_drr": 22.8,
      "trial_avg_drr": 46.23,
      "pre_asp_avg_drr": 67.7,
      "delta_vs_baseline": -0.5029,
      "delta_vs_pre_avg": -0.3172,
      "yesterday_24h_share": 1.0,
      "trial_avg_24h_share": 0.9964,
      "drr_day_on_day_swing": -0.5
    },
    {
      "hub_name": "Iwopin Ogun",
      "hub_id": 278,
      "yesterday_drr": 41.44,
      "trial_avg_drr": 48.0,
      "pre_asp_avg_drr": 36.25,
      "delta_vs_baseline": -0.5514,
      "delta_vs_pre_avg": 0.3241,
      "yesterday_24h_share": 0.963,
      "trial_avg_24h_share": 0.8632,
      "drr_day_on_day_swing": -0.3547
    },
    {
      "hub_name": "Ibiade Ogun",
      "hub_id": 279,
      "yesterday_drr": 71.28,
      "trial_avg_drr": 89.58,
      "pre_asp_avg_drr": 78.25,
      "delta_vs_baseline": -0.2408,
      "delta_vs_pre_avg": 0.1449,
      "yesterday_24h_share": 0.766,
      "trial_avg_24h_share": 0.8198,
      "drr_day_on_day_swing": -0.3522
    },
    {
      "hub_name": "Ute Ondo",
      "hub_id": 296,
      "yesterday_drr": 125.0,
      "trial_avg_drr": 87.52,
      "pre_asp_avg_drr": 93.04,
      "delta_vs_baseline": -0.571,
      "delta_vs_pre_avg": -0.0593,
      "yesterday_24h_share": 1.0,
      "trial_avg_24h_share": 0.9569,
      "drr_day_on_day_swing": 0.2791
    },
    {
      "hub_name": "Sobe Edo",
      "hub_id": 300,
      "yesterday_drr": 54.55,
      "trial_avg_drr": 31.56,
      "pre_asp_avg_drr": 29.6,
      "delta_vs_baseline": -0.7207,
      "delta_vs_pre_avg": 0.0664,
      "yesterday_24h_share": 1.0,
      "trial_avg_24h_share": 0.5922,
      "drr_day_on_day_swing": -0.2
    },
    {
      "hub_name": "Oba Akoko Ondo",
      "hub_id": 313,
      "yesterday_drr": 55.0,
      "trial_avg_drr": 82.31,
      "pre_asp_avg_drr": 103.74,
      "delta_vs_baseline": -0.4585,
      "delta_vs_pre_avg": -0.2065,
      "yesterday_24h_share": 1.0,
      "trial_avg_24h_share": 0.976,
      "drr_day_on_day_swing": -0.45
    }
  ]
}