{"generated_at": "2026-05-05T07:11:58.068081+00:00", "window_start": "2026-04-28", "window_end": "2026-05-04", "wig_current": 0.1611, "wig_prior": 0.1555, "portfolios": [{"name": "MPNG (directly operated)", "hub_count": 7, "drr_usd": 0.1611}], "regions": [{"region": "Ekiti", "hubs": 7, "drr_usd": 0.1611}], "lead_relative": {"above_threshold": 98, "total_agents": 100, "flagged_agents": 2}, "lead_earnings": {"above_floor": 84, "total_agents": 100, "below_floor": 16}, "flagged_agents": [{"agent_name": "Ayenuro Benjamin", "hub_name": "Igbokoda 5 Ondo", "region": "Ondo South", "portfolio": "MPNG (directly operated)", "agent_drr": 2.3461, "rel_perf": 21.0, "weekly_ngn": 23000, "days_in_role": 1313, "hub_drr": 0}, {"agent_name": "Abdulsalam Abiola", "hub_name": "Iwopin Ogun", "region": "Ondo South", "portfolio": "MPNG (directly operated)", "agent_drr": 1.2394, "rel_perf": 31.5, "weekly_ngn": 12150, "days_in_role": 1293, "hub_drr": 0}], "new_agents": {"by_region": [{"region": "Ekiti", "new_agents": 2, "avg_drr": 12.2426, "above_target": 2, "progressing": 0, "below_baseline": 0}, {"region": "Ondo North", "new_agents": 2, "avg_drr": 8.8229, "above_target": 2, "progressing": 0, "below_baseline": 0}, {"region": "Anambra", "new_agents": 8, "avg_drr": 6.4773, "above_target": 7, "progressing": 0, "below_baseline": 1}, {"region": "Delta", "new_agents": 9, "avg_drr": 5.6783, "above_target": 9, "progressing": 0, "below_baseline": 0}, {"region": "Enugu", "new_agents": 7, "avg_drr": 5.501, "above_target": 7, "progressing": 0, "below_baseline": 0}, {"region": "Bayelsa", "new_agents": 4, "avg_drr": 5.3808, "above_target": 2, "progressing": 0, "below_baseline": 2}, {"region": "Osun", "new_agents": 2, "avg_drr": 4.9258, "above_target": 2, "progressing": 0, "below_baseline": 0}, {"region": "Ondo South", "new_agents": 2, "avg_drr": 3.5702, "above_target": 2, "progressing": 0, "below_baseline": 0}, {"region": "Ebonyi", "new_agents": 3, "avg_drr": 3.5192, "above_target": 3, "progressing": 0, "below_baseline": 0}, {"region": "Imo", "new_agents": 39, "avg_drr": 2.4363, "above_target": 37, "progressing": 1, "below_baseline": 1}, {"region": "Kano", "new_agents": 18, "avg_drr": 1.6543, "above_target": 13, "progressing": 1, "below_baseline": 4}, {"region": "Cross River", "new_agents": 3, "avg_drr": 1.3771, "above_target": 1, "progressing": 0, "below_baseline": 2}, {"region": "Oyo", "new_agents": 1, "avg_drr": 1.3261, "above_target": 1, "progressing": 0, "below_baseline": 0}]}}